behave_odoo/__init__.py
behave_odoo/behave_odoo.py
behave_odoo-14.0.1.0.0.dist-info/LICENSE
behave_odoo-14.0.1.0.0.dist-info/METADATA
behave_odoo-14.0.1.0.0.dist-info/WHEEL
behave_odoo-14.0.1.0.0.dist-info/top_level.txt
behave_odoo-14.0.1.0.0.dist-info/RECORD
