Metadata-Version: 2.1
Name: behave-odoo
Version: 14.0.1.0.0
Summary: Helper functions for simplifying the process of writing behave tests for Odoo
Home-page: https://github.com/coopdevs/behave_odoo
Author: Coopdevs
Author-email: pelayo.garcia@coopdevs.org
License: AGPLv3
Classifier: Development Status :: 4 - Beta
Classifier: License :: OSI Approved :: GNU Affero General Public License v3
Classifier: Programming Language :: Python
Classifier: Programming Language :: Python :: 3
Classifier: Programming Language :: Python :: 3.7
Classifier: Programming Language :: Python :: 3.8
Classifier: Programming Language :: Python :: 3.9
Classifier: Programming Language :: Python :: 3.10
Classifier: Framework :: Odoo
Classifier: Framework :: Odoo :: 14.0
Classifier: Topic :: Software Development
Classifier: Topic :: Software Development :: Testing
Classifier: Topic :: Software Development :: Testing :: Acceptance
Classifier: Topic :: Software Development :: Testing :: BDD
Classifier: Intended Audience :: Developers
Classifier: Intended Audience :: Information Technology
Classifier: Intended Audience :: System Administrators
Classifier: Operating System :: OS Independent
License-File: LICENSE
Requires-Dist: selenium
Requires-Dist: behave
